pyjiaxun/__init__.py
pyjiaxun/crawl.py
pyjiaxun/data.py
pyjiaxun/start.py
pyjiaxun-0.1.0.dist-info/entry_points.txt
pyjiaxun-0.1.0.dist-info/LICENSE
pyjiaxun-0.1.0.dist-info/METADATA
pyjiaxun-0.1.0.dist-info/WHEEL
pyjiaxun-0.1.0.dist-info/RECORD
